bitwarden_rest_client/__init__.py
bitwarden_rest_client/models.py
bitwarden_rest_client/py.typed
bitwarden_rest_client/_async/__init__.py
bitwarden_rest_client/_async/client.py
bitwarden_rest_client/_sync/__init__.py
bitwarden_rest_client/_sync/client.py
bitwarden_rest_client/cli/__init__.py
bitwarden_rest_client/cli/__main__.py
bitwarden_rest_client/cli/app.py
bitwarden_rest_client-0.1.10.dist-info/METADATA
bitwarden_rest_client-0.1.10.dist-info/WHEEL
bitwarden_rest_client-0.1.10.dist-info/entry_points.txt
bitwarden_rest_client-0.1.10.dist-info/licenses/LICENSE
bitwarden_rest_client-0.1.10.dist-info/RECORD
